LICENCE.txt
MANIFEST.in
README.rst
pyproject.toml
setup.cfg
setup.py
djangocodemirror/__init__.py
djangocodemirror/apps.py
djangocodemirror/exceptions.py
djangocodemirror/fields.py
djangocodemirror/helper.py
djangocodemirror/manifest.py
djangocodemirror/settings.py
djangocodemirror/widgets.py
djangocodemirror.egg-info/PKG-INFO
djangocodemirror.egg-info/SOURCES.txt
djangocodemirror.egg-info/dependency_links.txt
djangocodemirror.egg-info/requires.txt
djangocodemirror.egg-info/top_level.txt
djangocodemirror.egg-info/zip-safe
djangocodemirror/static/CodeMirror/AUTHORS
djangocodemirror/static/CodeMirror/LICENSE
djangocodemirror/static/CodeMirror/README.md
djangocodemirror/static/CodeMirror/addon/comment/comment.js
djangocodemirror/static/CodeMirror/addon/comment/continuecomment.js
djangocodemirror/static/CodeMirror/addon/dialog/dialog.css
djangocodemirror/static/CodeMirror/addon/dialog/dialog.js
djangocodemirror/static/CodeMirror/addon/display/autorefresh.js
djangocodemirror/static/CodeMirror/addon/display/fullscreen.css
djangocodemirror/static/CodeMirror/addon/display/fullscreen.js
djangocodemirror/static/CodeMirror/addon/display/panel.js
djangocodemirror/static/CodeMirror/addon/display/placeholder.js
djangocodemirror/static/CodeMirror/addon/display/rulers.js
djangocodemirror/static/CodeMirror/addon/edit/closebrackets.js
djangocodemirror/static/CodeMirror/addon/edit/closetag.js
djangocodemirror/static/CodeMirror/addon/edit/continuelist.js
djangocodemirror/static/CodeMirror/addon/edit/matchbrackets.js
djangocodemirror/static/CodeMirror/addon/edit/matchtags.js
djangocodemirror/static/CodeMirror/addon/edit/trailingspace.js
djangocodemirror/static/CodeMirror/addon/fold/brace-fold.js
djangocodemirror/static/CodeMirror/addon/fold/comment-fold.js
djangocodemirror/static/CodeMirror/addon/fold/foldcode.js
djangocodemirror/static/CodeMirror/addon/fold/foldgutter.css
djangocodemirror/static/CodeMirror/addon/fold/foldgutter.js
djangocodemirror/static/CodeMirror/addon/fold/indent-fold.js
djangocodemirror/static/CodeMirror/addon/fold/markdown-fold.js
djangocodemirror/static/CodeMirror/addon/fold/xml-fold.js
djangocodemirror/static/CodeMirror/addon/hint/anyword-hint.js
