Metadata-Version: 2.4
Name: djangocodemirror
Version: 3.0.0
Summary: A Django application to embed CodeMirror
Home-page: https://github.com/sveetch/djangocodemirror
Author: David Thenon
Author-email: sveetch@gmail.com
License: MIT
Project-URL: Source Code, https://github.com/sveetch/djangocodemirror
Project-URL: Issue Tracker, https://github.com/sveetch/djangocodemirror/issues
Project-URL: Changelog, https://djangocodemirror.readthedocs.io/en/latest/history.html
Project-URL: Documentation, https://djangocodemirror.readthedocs.io/
Keywords: Python,Django,CodeMirror
Classifier: Development Status :: 5 - Production/Stable
Classifier: Intended Audience :: Developers
Classifier: License :: OSI Approved :: MIT License
Classifier: Natural Language :: English
Classifier: Programming Language :: Python :: 3
Classifier: Programming Language :: Python :: 3.10
Classifier: Programming Language :: Python :: 3.11
Classifier: Programming Language :: Python :: 3.12
Classifier: Framework :: Django
Classifier: Framework :: Django :: 4.2
Classifier: Framework :: Django :: 5.0
Classifier: Framework :: Django :: 5.1
Classifier: Framework :: Django :: 5.2
Classifier: Framework :: Django :: 6.0
Classifier: Topic :: Internet :: WWW/HTTP
Classifier: Topic :: Internet :: WWW/HTTP :: Dynamic Content
Classifier: Topic :: Text Editors :: Text Processing
Classifier: Topic :: Software Development :: Libraries :: Python Modules
Requires-Python: >=3.10
License-File: LICENCE.txt
Requires-Dist: Django>=4.2
Provides-Extra: dev
Requires-Dist: pytest>=7.0.0; extra == "dev"
Requires-Dist: pytest-django>=4.0.0; extra == "dev"
Requires-Dist: factory-boy>=3.3.0; extra == "dev"
Requires-Dist: pyquery>=2.0.0; extra == "dev"
Requires-Dist: freezegun>=1.2.0; extra == "dev"
Provides-Extra: quality
Requires-Dist: flake8>=6.0.0; extra == "quality"
Requires-Dist: tox>=4.11.0; extra == "quality"
Provides-Extra: doc
Requires-Dist: sphinx>=8.0.2; extra == "doc"
Requires-Dist: furo>=2024.8.6; extra == "doc"
Requires-Dist: sphinx-copybutton>=0.5.2; extra == "doc"
Provides-Extra: doc-live
Requires-Dist: livereload>=2.6.0; extra == "doc-live"
Provides-Extra: release
Requires-Dist: twine>=5.0.0; extra == "release"
Dynamic: license-file
